glaium/__init__.py
glaium/_version.py
glaium/agent.py
glaium/auth.py
glaium/client.py
glaium/exceptions.py
glaium/models.py
glaium/py.typed
glaium/retry.py
glaium/extras/__init__.py
glaium/extras/data.py
glaium/extras/handsup.py
glaium/extras/memory.py
glaium/extras/verification.py
glaium/reasoners/__init__.py
glaium/reasoners/analytical.py
glaium/reasoners/base.py
glaium/reasoners/models.py
glaium-0.3.0.dist-info/METADATA
glaium-0.3.0.dist-info/WHEEL
glaium-0.3.0.dist-info/licenses/LICENSE
glaium-0.3.0.dist-info/RECORD
