Metadata-Version: 2.4
Name: glaium
Version: 0.3.0
Summary: Python SDK for building autonomous agents that optimize toward organizational goals
Project-URL: Homepage, https://glaium.com
Project-URL: Repository, https://bitbucket.org/glaium/sdk
Project-URL: Issues, https://bitbucket.org/glaium/sdk/issues
Author-email: Glaium <support@glaium.com>
License-Expression: MIT
License-File: LICENSE
Keywords: agents,ai,autonomous,machine-learning,optimization,sdk
Classifier: Development Status :: 4 - Beta
Classifier: Intended Audience :: Developers
Classifier: License :: OSI Approved :: MIT License
Classifier: Operating System :: OS Independent
Classifier: Programming Language :: Python :: 3
Classifier: Programming Language :: Python :: 3.9
Classifier: Programming Language :: Python :: 3.10
Classifier: Programming Language :: Python :: 3.11
Classifier: Programming Language :: Python :: 3.12
Classifier: Topic :: Scientific/Engineering :: Artificial Intelligence
Classifier: Topic :: Software Development :: Libraries :: Python Modules
Classifier: Typing :: Typed
Requires-Python: >=3.9
Requires-Dist: httpx>=0.25.0
Requires-Dist: pydantic>=2.0.0
Provides-Extra: all
Requires-Dist: black>=23.0.0; extra == 'all'
Requires-Dist: mypy>=1.0.0; extra == 'all'
Requires-Dist: numpy>=1.21.0; extra == 'all'
Requires-Dist: pandas>=1.3.0; extra == 'all'
Requires-Dist: pyjwt>=2.0.0; extra == 'all'
Requires-Dist: pytest-asyncio>=0.21.0; extra == 'all'
Requires-Dist: pytest-cov>=4.0.0; extra == 'all'
Requires-Dist: pytest>=7.0.0; extra == 'all'
Requires-Dist: ruff>=0.1.0; extra == 'all'
Provides-Extra: analytical
Requires-Dist: numpy>=1.21.0; extra == 'analytical'
Requires-Dist: pandas>=1.3.0; extra == 'analytical'
Requires-Dist: prophet>=1.1.0; extra == 'analytical'
Provides-Extra: dev
Requires-Dist: black>=23.0.0; extra == 'dev'
Requires-Dist: mypy>=1.0.0; extra == 'dev'
Requires-Dist: pytest-asyncio>=0.21.0; extra == 'dev'
Requires-Dist: pytest-cov>=4.0.0; extra == 'dev'
Requires-Dist: pytest>=7.0.0; extra == 'dev'
Requires-Dist: ruff>=0.1.0; extra == 'dev'
Provides-Extra: jwt
Requires-Dist: pyjwt>=2.0.0; extra == 'jwt'
Provides-Extra: reasoners
Requires-Dist: numpy>=1.21.0; extra == 'reasoners'
Requires-Dist: pandas>=1.3.0; extra == 'reasoners'
